<recording>
  <id>6e35e3b2778883f5db637d7a5dba0a427f692e91-1344527193990</id>
  <state>available</state>
  <published>true</published>
  <start_time>1344527197274</start_time>
  <end_time>1344527311159</end_time>
  <playback>
    <format>presentation</format>
    <link>${URL}/playback/presentation/playback.html?meetingId=6e35e3b2778883f5db637d7a5dba0a427f692e91-1344527193990</link>
  </playback>
  <meta>
    <title>English 101</title>
    <meetingId>English 101</meetingId>
    <description>checking if presentation works</description>
    <email>Chad</email>
    <meetingName>English 101</meetingName>
  </meta>
</recording>
